django_d1/__init__.py
django_d1/base.py
django_d1/client.py
django_d1/creation.py
django_d1/database.py
django_d1/features.py
django_d1/introspection.py
django_d1/operations.py
django_d1/schema.py
django_dbms/__init__.py
django_dbms/base.py
django_d1db-0.0.10.dist-info/LICENSE
django_d1db-0.0.10.dist-info/METADATA
django_d1db-0.0.10.dist-info/WHEEL
django_d1db-0.0.10.dist-info/top_level.txt
django_d1db-0.0.10.dist-info/RECORD
