Metadata-Version: 2.1
Name: django-d1db
Version: 0.0.10
Summary: Django backend for Cloudflare D1
Author: Gabriel Massadas
Project-URL: Bug Reports, https://github.com/G4brym/django-d1/issues
Project-URL: Source, https://github.com/G4brym/django-d1
Classifier: Development Status :: 3 - Alpha
Classifier: Framework :: Django
Classifier: Framework :: Django :: 5.0
Classifier: License :: OSI Approved :: MIT License
Classifier: Operating System :: OS Independent
Classifier: Programming Language :: Python
Classifier: Programming Language :: Python :: 3
Classifier: Programming Language :: Python :: 3.10
Classifier: Programming Language :: Python :: 3.11
Classifier: Programming Language :: Python :: 3.12
Requires-Python: >=3.10
License-File: LICENSE
Requires-Dist: websocket-client
